{"web":[{"value":["录取通知书","接受","录取通知"],"key":"Accepted"},{"value":["保付支票","已受理的支票"],"key":"accepted check"},{"value":["通用的","普遍承认的","普遍接受"],"key":"generally accepted"}],"query":"accepted","translation":["接受"],"errorCode":"0","dict":{"url":"yddict://m.youdao.com/dict?le=eng&q=accepted"},"webdict":{"url":"http://m.youdao.com/dict?le=eng&q=accepted"},"basic":{"us-phonetic":"ək'sɛptɪd","phonetic":"ək'septɪd","uk-phonetic":"ək'septɪd","explains":["v. 接受（accept的过去式及过去分词）","adj. 公认的；录取的；可接受的；已承兑的"]},"l":"EN2zh-CHS"}
