{"web":[{"value":["习惯的","通常的","惯常的"],"key":"accustomed"},{"value":["运输费","酬劳费","酬劳费，运输费"],"key":"accustomed averages"},{"value":["小额费用","小额费用(如码头费、引航费等)","照常规办理单独海损免赔额"],"key":"average accustomed"}],"query":"accustomed","translation":["习惯了"],"errorCode":"0","dict":{"url":"yddict://m.youdao.com/dict?le=eng&q=accustomed"},"webdict":{"url":"http://m.youdao.com/dict?le=eng&q=accustomed"},"basic":{"us-phonetic":"ə'kʌstəmd","phonetic":"ə'kʌstəmd","uk-phonetic":"ə'kʌstəmd","explains":["v. 使习惯于（accustom的过去分词）","adj. 习惯的；通常的；独有的"]},"l":"EN2zh-CHS"}
