{"web":[{"value":["高级","先进","高级设置"],"key":"advanced"},{"value":["先进材料","先进材料","高级材料"],"key":"Advanced Materials"},{"value":["大学先修课程","大学先修课程","大学预修课程"],"key":"Advanced Placement"}],"query":"advanced","translation":["先进的"],"errorCode":"0","dict":{"url":"yddict://m.youdao.com/dict?le=eng&q=advanced"},"webdict":{"url":"http://m.youdao.com/dict?le=eng&q=advanced"},"basic":{"us-phonetic":"əd'vænst","phonetic":"ədˈvɑ:nst","uk-phonetic":"ədˈvɑ:nst","explains":["adj. 先进的；高级的；晚期的；年老的","v. 前进；增加；上涨（advance的过去式和过去分词形式）"]},"l":"EN2zh-CHS"}
