{"web":[{"value":["改变","变更","改动"],"key":"alter"},{"value":["修改数据库","修改数据库的权限","库级别上的操作"],"key":"ALTER DATABASE"},{"value":["阿尔特","奥尔特","艾尔特"],"key":"Robert Alter"}],"query":"alter","translation":["改变"],"errorCode":"0","dict":{"url":"yddict://m.youdao.com/dict?le=eng&q=alter"},"webdict":{"url":"http://m.youdao.com/dict?le=eng&q=alter"},"basic":{"us-phonetic":"'ɔltɚ","phonetic":"'ɔːltə; 'ɒl-","uk-phonetic":"'ɔːltə; 'ɒl-","explains":["vt. 改变，更改","vi. 改变；修改","n. (Alter)人名；(英)奥尔特；(德、捷、葡、爱沙、立陶、拉脱、俄、西、罗、瑞典)阿尔特"]},"l":"EN2zh-CHS"}
