{"web":[{"value":["沥青","柏油","狂野飙车系列"],"key":"asphalt"},{"value":["狂野飙车5","都市赛车","狂野飙车"],"key":"Asphalt 5"},{"value":["沥青混凝土","地沥青混凝土","沥青砼"],"key":"asphalt concrete"}],"query":"asphalt","translation":["沥青"],"errorCode":"0","dict":{"url":"yddict://m.youdao.com/dict?le=eng&q=asphalt"},"webdict":{"url":"http://m.youdao.com/dict?le=eng&q=asphalt"},"basic":{"us-phonetic":"'æsfɔlt","phonetic":"'æsfælt; -əlt","uk-phonetic":"'æsfælt; -əlt","explains":["n. 沥青；柏油","adj. 用柏油铺成的","vt. 以沥青铺"]},"l":"EN2zh-CHS"}
