{"web":[{"value":["辅助的","助动词","补助的"],"key":"auxiliary"},{"value":["辅警","协警","辅助警察"],"key":"Auxiliary police"},{"value":["辅助视图","辅助图","辅助圆"],"key":"auxiliary view"}],"query":"auxiliary","translation":["辅助的"],"errorCode":"0","dict":{"url":"yddict://m.youdao.com/dict?le=eng&q=auxiliary"},"webdict":{"url":"http://m.youdao.com/dict?le=eng&q=auxiliary"},"basic":{"us-phonetic":"ɔːɡ'zɪlɪəri","phonetic":"ɔːg'zɪlɪərɪ; ɒg-","uk-phonetic":"ɔːg'zɪlɪərɪ; ɒg-","explains":["n. 助动词；辅助者，辅助物；附属机构","adj. 辅助的；副的；附加的"]},"l":"EN2zh-CHS"}
