{"web":[{"value":["长枕","长枕套","垫板"],"key":"bolster"},{"value":["锚架","锚链孔唇口","锚承架"],"key":"anchor bolster"},{"value":["锚链管孔磨材","锚链孔唇口","锚链枕垫"],"key":"hawse bolster"}],"query":"bolster","translation":["支持"],"errorCode":"0","dict":{"url":"yddict://m.youdao.com/dict?le=eng&q=bolster"},"webdict":{"url":"http://m.youdao.com/dict?le=eng&q=bolster"},"basic":{"us-phonetic":"'bolstɚ","phonetic":"'bəʊlstə","uk-phonetic":"'bəʊlstə","explains":["n. 支持；长枕","vt. 支持；支撑","n. (Bolster)人名；(英)博尔斯特"]},"l":"EN2zh-CHS"}
