{"web":[{"value":["候选人","参选人","候选"],"key":"Candidate"},{"value":["候选函式","候选函数"],"key":"candidate function"},{"value":["降落伞候选人","外来候选人","降落伞候选人;外来候选人"],"key":"parachute candidate"}],"query":"candidate","translation":["候选人"],"errorCode":"0","dict":{"url":"yddict://m.youdao.com/dict?le=eng&q=candidate"},"webdict":{"url":"http://m.youdao.com/dict?le=eng&q=candidate"},"basic":{"us-phonetic":"ˈkændɪˌdet, -dɪt","phonetic":"'kændɪdeɪt; -dət","uk-phonetic":"'kændɪdeɪt; -dət","explains":["n. 候选人，候补者；应试者"]},"l":"EN2zh-CHS"}
