{"web":[{"value":["迷人的","使人神魂颠倒的","有魅力的"],"key":"captivating"},{"value":["蛊惑吸血鬼"],"key":"Captivating Vampire"},{"value":["迷人的意见"],"key":"Captivating Views"}],"query":"captivating","translation":["迷人的"],"errorCode":"0","dict":{"url":"yddict://m.youdao.com/dict?le=eng&q=captivating"},"webdict":{"url":"http://m.youdao.com/dict?le=eng&q=captivating"},"basic":{"us-phonetic":"'kæptiveitiŋ","phonetic":"'kæptɪveɪtɪŋ","uk-phonetic":"'kæptɪveɪtɪŋ","explains":["adj. 迷人的；有魅力的","v. 使\u2026着迷（captivate的ing形式）"]},"l":"EN2zh-CHS"}
