{"web":[{"value":["分门别类","分类","类型化"],"key":"categorization"},{"value":["文本分类","文件分类","文本"],"key":"text categorization"},{"value":["初步归类"],"key":"primitive Categorization"}],"query":"categorization","translation":["分类"],"errorCode":"0","dict":{"url":"yddict://m.youdao.com/dict?le=eng&q=categorization"},"webdict":{"url":"http://m.youdao.com/dict?le=eng&q=categorization"},"basic":{"us-phonetic":",kætəgərɪ'zeʃən","phonetic":",kætigəri'zeiʃən","uk-phonetic":",kætigəri'zeiʃən","explains":["n. 分类；分门别类；编目方法"]},"l":"EN2zh-CHS"}
