{"web":[{"value":["巧合","一致","符合"],"key":"coincidence"},{"value":["重合放大器","符合放大器"],"key":"coincidence amplifier"},{"value":["符合电路","重合电路","符合线路"],"key":"coincidence circuit"}],"query":"coincidence","translation":["巧合"],"errorCode":"0","dict":{"url":"yddict://m.youdao.com/dict?le=eng&q=coincidence"},"webdict":{"url":"http://m.youdao.com/dict?le=eng&q=coincidence"},"basic":{"us-phonetic":"ko'ɪnsɪdəns","phonetic":"kəʊ'ɪnsɪd(ə)ns","uk-phonetic":"kəʊ'ɪnsɪd(ə)ns","explains":["n. 巧合；一致；同时发生"]},"l":"EN2zh-CHS"}
