{"web":[{"value":["冷血的","变温动物","冷酷的"],"key":"cold-blooded"},{"value":["冷血杀人"],"key":"cold-blooded killing"},{"value":["冷血的人"],"key":"Cold-blooded persons"}],"query":"cold-blooded","translation":["冷血动物"],"errorCode":"0","dict":{"url":"yddict://m.youdao.com/dict?le=eng&q=cold-blooded"},"webdict":{"url":"http://m.youdao.com/dict?le=eng&q=cold-blooded"},"basic":{"us-phonetic":"'kəuld'blʌdid","phonetic":"'kəuld'blʌdid","uk-phonetic":"'kəuld'blʌdid","explains":["adj. [生理] 冷血的；残酷的，无情的；怕冷的"]},"l":"EN2zh-CHS"}
