{"web":[{"value":["心满意足","满足的","自得"],"key":"Contented"},{"value":["适度幸福组"],"key":"the Contented"},{"value":["基于内容","基于内容的"],"key":"contented based"}],"query":"contented","translation":["满足"],"errorCode":"0","dict":{"url":"yddict://m.youdao.com/dict?le=eng&q=contented"},"webdict":{"url":"http://m.youdao.com/dict?le=eng&q=contented"},"basic":{"us-phonetic":"kən'tɛntɪd","phonetic":"kən'tentɪd","uk-phonetic":"kən'tentɪd","explains":["v. 使\u2026满足；使\u2026安心（content的过去式和过去分词）","adj. 满足的；心安的"]},"l":"EN2zh-CHS"}
