{"web":[{"value":["心理咨询","咨询","疏导"],"key":"Counseling"},{"value":["遗传咨询","遗传咨询","遗传谘询"],"key":"Genetic counseling"},{"value":["热线辅导","电话咨询","热线辅导"],"key":"Telephone counseling"}],"query":"counseling","translation":["咨询"],"errorCode":"0","dict":{"url":"yddict://m.youdao.com/dict?le=eng&q=counseling"},"webdict":{"url":"http://m.youdao.com/dict?le=eng&q=counseling"},"basic":{"us-phonetic":"'kaʊnslɪŋ","phonetic":"'kaunsəliŋ","uk-phonetic":"'kaunsəliŋ","explains":["n. 咨询服务","v. 建议；劝告；商讨（counsel的ing形式）"]},"l":"EN2zh-CHS"}
