{"web":[{"value":["克雷森特","月牙形","新月"],"key":"Crescent"},{"value":["皇家新月","皇家新月楼","新月形王宫"],"key":"Royal Crescent"},{"value":["金新月","金新月","西亚金新月"],"key":"Golden Crescent"}],"query":"crescent","translation":["新月"],"errorCode":"0","dict":{"url":"yddict://m.youdao.com/dict?le=eng&q=crescent"},"webdict":{"url":"http://m.youdao.com/dict?le=eng&q=crescent"},"basic":{"us-phonetic":"'krɛsnt","phonetic":"'kresənt","uk-phonetic":"'kresənt","explains":["n. 新月；新月状物；伊斯兰教的标记；土耳其的新月形国徽","adj. 新月形的；逐渐增加的","vt. 以新月形物装饰；使成新月形","n. (Crescent)人名；(法)克雷桑"]},"l":"EN2zh-CHS"}
