{"web":[{"value":["猛冲","连接号","破折号"],"key":"dash"},{"value":["Dietary Approaches to Stop Hypertension"],"key":"DASH"},{"value":["象声号","象声号"],"key":"Wave dash"}],"query":"dash","translation":["破折号"],"errorCode":"0","dict":{"url":"yddict://m.youdao.com/dict?le=eng&q=dash"},"webdict":{"url":"http://m.youdao.com/dict?le=eng&q=dash"},"basic":{"us-phonetic":"dæʃ","phonetic":"dæʃ","uk-phonetic":"dæʃ","explains":["n. 破折号；冲撞","vi. 猛冲；撞击","vt. 使\u2026破灭；猛撞；泼溅","n. (Dash)人名；(英、印)达什；(蒙)达希"]},"l":"EN2zh-CHS"}
