{"web":[{"value":["欣喜的","愉快的","高兴的"],"key":"delighted"},{"value":["惬意体验"],"key":"Delighted Experience"},{"value":["和高兴","欣喜"],"key":"and delighted"}],"query":"delighted","translation":["很高兴"],"errorCode":"0","dict":{"url":"yddict://m.youdao.com/dict?le=eng&q=delighted"},"webdict":{"url":"http://m.youdao.com/dict?le=eng&q=delighted"},"basic":{"us-phonetic":"dɪ'laɪtɪd","phonetic":"dɪ'laɪtɪd","uk-phonetic":"dɪ'laɪtɪd","explains":["adj. 高兴的；欣喜的","v. 使\u2026兴高采烈；感到快乐（delight的过去分词）"]},"l":"EN2zh-CHS"}
