{"web":[{"value":["满目疮痍","哀鸿遍野","毁坏的"],"key":"Devastated"},{"value":["极为震惊"],"key":"devastated  devastating"},{"value":["荒芜的土地","荒废地"],"key":"devastated land"}],"query":"devastated","translation":["摧毁了"],"errorCode":"0","dict":{"url":"yddict://m.youdao.com/dict?le=eng&q=devastated"},"webdict":{"url":"http://m.youdao.com/dict?le=eng&q=devastated"},"basic":{"us-phonetic":"'dɛvəstetɪd","phonetic":"'devəsteɪtid","uk-phonetic":"'devəsteɪtid","explains":["v. 毁坏；摧毁（devastate的过去式和过去分词）","adj. 毁坏的；极为震惊的"]},"l":"EN2zh-CHS"}
