{"web":[{"value":["勤奋","勤勉的","勤于"],"key":"Diligent"},{"value":["学员风采"],"key":"Diligent Participants"},{"value":["勤奋的"],"key":"diligent hardworking"}],"query":"diligent","translation":["勤勉的"],"errorCode":"0","dict":{"url":"yddict://m.youdao.com/dict?le=eng&q=diligent"},"webdict":{"url":"http://m.youdao.com/dict?le=eng&q=diligent"},"basic":{"us-phonetic":"'dɪlɪdʒənt","phonetic":"'dɪlɪdʒ(ə)nt","uk-phonetic":"'dɪlɪdʒ(ə)nt","explains":["adj. 勤勉的；用功的，费尽心血的","n. (Diligent)人名；(法)迪利让"]},"l":"EN2zh-CHS"}
