{"web":[{"value":["残疾人","残疾的","伤残的"],"key":"Disabled"},{"value":["残疾人专用","身心障碍专用电梯"],"key":"Disabled Only"},{"value":["残疾人","残废人","残障人士"],"key":"disabled people"}],"query":"disabled","translation":["禁用"],"errorCode":"0","dict":{"url":"yddict://m.youdao.com/dict?le=eng&q=disabled"},"webdict":{"url":"http://m.youdao.com/dict?le=eng&q=disabled"},"basic":{"us-phonetic":"dɪs'ebld","phonetic":"dɪs'eɪbld","uk-phonetic":"dɪs'eɪbld","explains":["adj. 残废的，有缺陷的","v. 使\u2026失去能力（disable的过去分词）"]},"l":"EN2zh-CHS"}
