{"web":[{"value":["扭曲的","歪了","失真效果器"],"key":"distorted"},{"value":["畸变水","变态水","畸变水(气)"],"key":"distorted water"},{"value":["变态混凝土","变态混凝上"],"key":"distorted concrete"}],"query":"distorted","translation":["扭曲的"],"errorCode":"0","dict":{"url":"yddict://m.youdao.com/dict?le=eng&q=distorted"},"webdict":{"url":"http://m.youdao.com/dict?le=eng&q=distorted"},"basic":{"us-phonetic":"dɪs'tɔrtɪd","phonetic":"dɪ'stɔːtɪd","uk-phonetic":"dɪ'stɔːtɪd","explains":["v. 扭曲（distort的过去式和过去分词）","adj. 歪曲的；受到曲解的"]},"l":"EN2zh-CHS"}
