{"web":[{"value":["排除","排斥","拒绝"],"key":"Exclusion"},{"value":["排除标准","排除条件","排除标准"],"key":"Exclusion criteria"},{"value":["禁止区","禁区","禁入区"],"key":"exclusion area"}],"query":"exclusion","translation":["排除"],"errorCode":"0","dict":{"url":"yddict://m.youdao.com/dict?le=eng&q=exclusion"},"webdict":{"url":"http://m.youdao.com/dict?le=eng&q=exclusion"},"basic":{"us-phonetic":"ɪk'skluʒn","phonetic":"ɪk'skluːʒ(ə)n; ek-","uk-phonetic":"ɪk'skluːʒ(ə)n; ek-","explains":["n. 排除；排斥；驱逐；被排除在外的事物"]},"l":"EN2zh-CHS"}
