{"web":[{"value":["冗长辩论","冗长辩论","阻碍议案通过"],"key":"Filibuster"},{"value":["妨碍议事"],"key":"filibuster v"},{"value":["飞力博士的神奇水燃无热烟火","巫师的玩具"],"key":"Filibuster Fireworks"}],"query":"filibuster","translation":["阻挠议事的行动"],"errorCode":"0","dict":{"url":"yddict://m.youdao.com/dict?le=eng&q=filibuster"},"webdict":{"url":"http://m.youdao.com/dict?le=eng&q=filibuster"},"basic":{"us-phonetic":"'fɪlə'bʌstɚ","phonetic":"'fɪlɪbʌstə","uk-phonetic":"'fɪlɪbʌstə","explains":["n. 海盗；暴兵，掠夺兵；阻挠议事的议员；阻挠议事的行动","vt. 阻碍议案通过","vi. 掠夺；阻饶议事"]},"l":"EN2zh-CHS"}
