{"web":[{"value":["国内生产总值(Gross Domestic Product)","生产总值","地区生产总值"],"key":"GDP"},{"value":["Green gross domestic product","GGDP","Green GDP"],"key":"绿色GDP"},{"value":["Per Capita GDP","GDP per capita","GDPPC"],"key":"人均GDP"}],"query":"GDP","translation":["国内生产总值"],"errorCode":"0","dict":{"url":"yddict://m.youdao.com/dict?le=eng&q=GDP"},"webdict":{"url":"http://m.youdao.com/dict?le=eng&q=GDP"},"basic":{"us-phonetic":",dʒi: di: 'pi:","phonetic":",dʒi: di: 'pi:","uk-phonetic":",dʒi: di: 'pi:","explains":["abbr. 国内生产总值（Gross Domestic Product）；辉光放电聚合物（Glow Discharge Polymer）"]},"l":"EN2zh-CHS"}
