{"web":[{"value":["一般","综述","上将"],"key":"General"},{"value":["通用汽车","通用汽车公司","通用汽车公司"],"key":"General Motors"},{"value":["总书记","总干事","秘书长"],"key":"General Secretary"}],"query":"general","translation":["一般"],"errorCode":"0","dict":{"url":"yddict://m.youdao.com/dict?le=eng&q=general"},"webdict":{"url":"http://m.youdao.com/dict?le=eng&q=general"},"basic":{"us-phonetic":"'dʒɛnrəl","phonetic":"'dʒen(ə)r(ə)l","uk-phonetic":"'dʒen(ə)r(ə)l","explains":["n. 一般；将军，上将；常规","adj. 一般的，普通的；综合的；大体的","n. (General)人名；(英)杰纳勒尔"]},"l":"EN2zh-CHS"}
