{"web":[{"value":["整体的","全人","整体性"],"key":"Holistic"},{"value":["全面营销","全方位营销","全方位行销"],"key":"holistic marketing"},{"value":["整体性治理","整体治理","全局治理"],"key":"holistic governance"}],"query":"holistic","translation":["整体"],"errorCode":"0","dict":{"url":"yddict://m.youdao.com/dict?le=eng&q=holistic"},"webdict":{"url":"http://m.youdao.com/dict?le=eng&q=holistic"},"basic":{"us-phonetic":"ho'lɪstɪk","phonetic":"həʊ'lɪstɪk; hɒ-","uk-phonetic":"həʊ'lɪstɪk; hɒ-","explains":["adj. 整体的；全盘的"]},"l":"EN2zh-CHS"}
