{"web":[{"value":["理想主义的","唯心论的","唯心主义者的"],"key":"idealistic"},{"value":["政治上的意识形态"],"key":"idealistic perspective"},{"value":["是理想"],"key":"Be idealistic"}],"query":"idealistic","translation":["理想主义的"],"errorCode":"0","dict":{"url":"yddict://m.youdao.com/dict?le=eng&q=idealistic"},"webdict":{"url":"http://m.youdao.com/dict?le=eng&q=idealistic"},"basic":{"us-phonetic":"ai,diə'listik,-kəl","phonetic":",aɪdɪə'lɪstɪk; aɪ,dɪə'lɪstɪk; aɪ,diːə'lɪstɪk","uk-phonetic":",aɪdɪə'lɪstɪk; aɪ,dɪə'lɪstɪk; aɪ,diːə'lɪstɪk","explains":["adj. 理想主义的；唯心论的；唯心主义者的；空想家的"]},"l":"EN2zh-CHS"}
