{"web":[{"value":["国际","世界的","学生机票"],"key":"International"},{"value":["国际足球","国际足球","国际足坛"],"key":"International football"},{"value":["国际机场","香港国际机场","国际航空站"],"key":"international airport"}],"query":"international","translation":["国际的"],"errorCode":"0","dict":{"url":"yddict://m.youdao.com/dict?le=eng&q=international"},"webdict":{"url":"http://m.youdao.com/dict?le=eng&q=international"},"basic":{"us-phonetic":",ɪntɚ'næʃnəl","phonetic":"ɪntə'næʃ(ə)n(ə)l","uk-phonetic":"ɪntə'næʃ(ə)n(ə)l","explains":["n. 国际组织；国际体育比赛；外国居留者；国际股票","adj. 国际的；两国（或以上）国家的；超越国界的；国际关系的；世界的"]},"l":"EN2zh-CHS"}
