{"web":[{"value":["旅行指南","航海日程表","旅行计划"],"key":"itinerary"},{"value":["最终旅行路线","列后决定的行程表"],"key":"final itinerary"},{"value":["您的行程","你行程","您的行程安排"],"key":"your itinerary"}],"query":"itinerary","translation":["行程"],"errorCode":"0","dict":{"url":"yddict://m.youdao.com/dict?le=eng&q=itinerary"},"webdict":{"url":"http://m.youdao.com/dict?le=eng&q=itinerary"},"basic":{"us-phonetic":"aɪ'tɪnərɛri","phonetic":"aɪ'tɪn(ə)(rə)rɪ; ɪ-","uk-phonetic":"aɪ'tɪn(ə)(rə)rɪ; ɪ-","explains":["n. 旅程，路线； 旅行日程","adj. 旅程的； 巡回的，流动的"]},"l":"EN2zh-CHS"}
