{"web":[{"value":["键盘","键盘 (消歧义)","电脑键盘"],"key":"Keyboard"},{"value":["虚拟键盘","虚拟键盘","说明虚拟键盘"],"key":"Virtual keyboard"},{"value":["快捷键","键盘快捷键","键盘快捷命令"],"key":"keyboard shortcut"}],"query":"keyboard","translation":["键盘"],"errorCode":"0","dict":{"url":"yddict://m.youdao.com/dict?le=eng&q=keyboard"},"webdict":{"url":"http://m.youdao.com/dict?le=eng&q=keyboard"},"basic":{"us-phonetic":"'ki'bɔrd","phonetic":"'kiːbɔːd","uk-phonetic":"'kiːbɔːd","explains":["n. 键盘","vt. 键入；用键盘式排字机排字","vi. 用键盘进行操作；作键盘式排字机排字"]},"l":"EN2zh-CHS"}
