{"web":[{"value":["天然堤","河堤","防洪堤"],"key":"levee"},{"value":["堤坝裂口","决口","大坝绝口"],"key":"levee breach"},{"value":["堤防护岸","护堤壁"],"key":"levee revetment"}],"query":"levee","translation":["堤坝"],"errorCode":"0","dict":{"url":"yddict://m.youdao.com/dict?le=eng&q=levee"},"webdict":{"url":"http://m.youdao.com/dict?le=eng&q=levee"},"basic":{"us-phonetic":"'lɛvi","phonetic":"'levɪ; lɪ'viː","uk-phonetic":"'levɪ; lɪ'viː","explains":["n. 堤坝（码头）；（旧时君主或显贵的）早晨接见","n. (Levee)人名；(利比)莱维","vt. 为\u2026筑堤"]},"l":"EN2zh-CHS"}
