{"web":[{"value":["清盘","清算","清盘"],"key":"Liquidation"},{"value":["破产清算","破产清算"],"key":"Bankruptcy Liquidation"},{"value":["清算收入","清算收益","清算所得"],"key":"liquidation income"}],"query":"liquidation","translation":["清算"],"errorCode":"0","dict":{"url":"yddict://m.youdao.com/dict?le=eng&q=liquidation"},"webdict":{"url":"http://m.youdao.com/dict?le=eng&q=liquidation"},"basic":{"us-phonetic":",lɪkwɪ'deʃən","phonetic":"lɪkwɪ'deɪʃ(ə)n","uk-phonetic":"lɪkwɪ'deɪʃ(ə)n","explains":["n. 清算；偿还；液化；清除"]},"l":"EN2zh-CHS"}
