{"web":[{"value":["维持","保持","维护"],"key":"Maintain"},{"value":["保养准备金","保有储量","(飞机租赁中承租人承担的)保养准备金"],"key":"maintain reserves"},{"value":["坚持","维持"],"key":"maintain preserve"}],"query":"maintain","translation":["维护"],"errorCode":"0","dict":{"url":"yddict://m.youdao.com/dict?le=eng&q=maintain"},"webdict":{"url":"http://m.youdao.com/dict?le=eng&q=maintain"},"basic":{"us-phonetic":"men'ten","phonetic":"meɪn'teɪn; mən'teɪn","uk-phonetic":"meɪn'teɪn; mən'teɪn","explains":["vt. 维持；继续；维修；主张；供养"]},"l":"EN2zh-CHS"}
