{"web":[{"value":["金盏花","万寿菊","金盏花牌"],"key":"Marigold"},{"value":["万寿菊提取物","叶黄素","金盏花"],"key":"Marigold Extract"},{"value":["金盏花茶","金盏花"],"key":"marigold tea"}],"query":"marigold","translation":["金盏花"],"errorCode":"0","dict":{"url":"yddict://m.youdao.com/dict?le=eng&q=marigold"},"webdict":{"url":"http://m.youdao.com/dict?le=eng&q=marigold"},"basic":{"us-phonetic":"'mærɪɡold","phonetic":"'mærɪgəʊld","uk-phonetic":"'mærɪgəʊld","explains":["n. 万寿菊；金盏花","n. (Marigold)人名；(英)玛丽戈尔德"]},"l":"EN2zh-CHS"}
