{"web":[{"value":["公司犯罪","不当行为","不端行为"],"key":"misconduct"},{"value":["严重渎职","特别严重犯规","严重不端行为"],"key":"gross misconduct"},{"value":["严重不法行为","严重的不法行为"],"key":"aggravated misconduct"}],"query":"misconduct","translation":["不当行为"],"errorCode":"0","dict":{"url":"yddict://m.youdao.com/dict?le=eng&q=misconduct"},"webdict":{"url":"http://m.youdao.com/dict?le=eng&q=misconduct"},"basic":{"us-phonetic":",mɪs'kɑndʌkt","phonetic":"mɪs'kɒndʌkt","uk-phonetic":"mɪs'kɒndʌkt","explains":["n. 不端行为；处理不当","vt. 处理不当；行为不检"]},"l":"EN2zh-CHS"}
