{"web":[{"value":["专性的","使负义务","感恩"],"key":"obligate"},{"value":["专性需氧菌","专性需氧生物","专性需氧微生物"],"key":"obligate aerobe"},{"value":["厌氧菌","专性嫌气微生物","专性厌氧菌"],"key":"obligate anaerobes"}],"query":"obligate","translation":["专"],"errorCode":"0","dict":{"url":"yddict://m.youdao.com/dict?le=eng&q=obligate"},"webdict":{"url":"http://m.youdao.com/dict?le=eng&q=obligate"},"basic":{"us-phonetic":"'ɑblɪ,ɡeɪt","phonetic":"'ɒblɪgeɪt","uk-phonetic":"'ɒblɪgeɪt","explains":["vt. 使负义务；强使，强迫；对\u2026施以恩惠","adj. 有责任的，有义务的；必需的"]},"l":"EN2zh-CHS"}
