{"web":[{"value":["有人","占位","使用中"],"key":"Occupied"},{"value":["占用带宽","占用频带","占有带宽"],"key":"occupied bandwidth"},{"value":["满带","占有能带"],"key":"Occupied band"}],"query":"occupied","translation":["被占领的"],"errorCode":"0","dict":{"url":"yddict://m.youdao.com/dict?le=eng&q=occupied"},"webdict":{"url":"http://m.youdao.com/dict?le=eng&q=occupied"},"basic":{"us-phonetic":"'ɑkjupaɪd","phonetic":"'ɒkjʊpaɪd","uk-phonetic":"'ɒkjʊpaɪd","explains":["v. 占有（occupy的过去分词）","adj. 已占用的；使用中的；无空闲的"]},"l":"EN2zh-CHS"}
