{"web":[{"value":["橙色","橙子","橘黄色"],"key":"ORANGE"},{"value":["芝加哥捷运橘线","洛杉矶快速公交橙线","高雄捷运橘线"],"key":"Orange Line"},{"value":["国际橘","国际橘","国际标准橘"],"key":"International orange"}],"query":"orange","translation":["橙色的"],"errorCode":"0","dict":{"url":"yddict://m.youdao.com/dict?le=eng&q=orange"},"webdict":{"url":"http://m.youdao.com/dict?le=eng&q=orange"},"basic":{"us-phonetic":"'ɔrɪndʒ","phonetic":"'ɒrɪn(d)ʒ","uk-phonetic":"'ɒrɪn(d)ʒ","explains":["n. 橙；橙色；桔子","adj. 橙色的；橘色的","n. (Orange)人名；(英)奥林奇；(法)奥朗热"]},"l":"EN2zh-CHS"}
