{"web":[{"value":["完美主义","至善论","十全十美主义"],"key":"Perfectionism"},{"value":["完美主义的女人"],"key":"Perfectionism woman"},{"value":["反至善主义"],"key":"Anti Perfectionism"}],"query":"perfectionism","translation":["完美主义"],"errorCode":"0","dict":{"url":"yddict://m.youdao.com/dict?le=eng&q=perfectionism"},"webdict":{"url":"http://m.youdao.com/dict?le=eng&q=perfectionism"},"basic":{"us-phonetic":"pɚ'fɛkʃənɪzm","phonetic":"pə'fekʃ(ə)nɪz(ə)m","uk-phonetic":"pə'fekʃ(ə)nɪz(ə)m","explains":["n. 至善论；十全十美主义"]},"l":"EN2zh-CHS"}
