{"web":[{"value":["可允许的","可以的","容许的"],"key":"permissible"},{"value":["容许误差","允许误差","允许偏差"],"key":"permissible error"},{"value":["容许剂量","允许剂量","答应剂量"],"key":"permissible dose"}],"query":"permissible","translation":["允许的"],"errorCode":"0","dict":{"url":"yddict://m.youdao.com/dict?le=eng&q=permissible"},"webdict":{"url":"http://m.youdao.com/dict?le=eng&q=permissible"},"basic":{"us-phonetic":"pɚ'mɪsəbl","phonetic":"pə'mɪsɪb(ə)l","uk-phonetic":"pə'mɪsɪb(ə)l","explains":["adj. 可允许的；获得准许的"]},"l":"EN2zh-CHS"}
