{"web":[{"value":["医生","内科医生","内科医师"],"key":"physician"},{"value":["医师助理","医生助理","助理医师"],"key":"Physician Assistant"},{"value":["医师助理","医生助理","医师助理研究专业"],"key":"Physician Assistants"}],"query":"physician","translation":["医生"],"errorCode":"0","dict":{"url":"yddict://m.youdao.com/dict?le=eng&q=physician"},"webdict":{"url":"http://m.youdao.com/dict?le=eng&q=physician"},"basic":{"us-phonetic":"fɪ'zɪʃən","phonetic":"fɪ'zɪʃ(ə)n","uk-phonetic":"fɪ'zɪʃ(ə)n","explains":["n. [医] 医师；内科医师"]},"l":"EN2zh-CHS"}
