{"web":[{"value":["可能的","二级预测","合理的"],"key":"possible"},{"value":["可能储量","地质储量","预测储量"],"key":"possible reserves"},{"value":["爱之可能性","爱之有可能性","爱之大概性"],"key":"Possible Loves"}],"query":"possible","translation":["可能的"],"errorCode":"0","dict":{"url":"yddict://m.youdao.com/dict?le=eng&q=possible"},"webdict":{"url":"http://m.youdao.com/dict?le=eng&q=possible"},"basic":{"us-phonetic":"'pɑsəbl","phonetic":"'pɒsɪb(ə)l","uk-phonetic":"'pɒsɪb(ə)l","explains":["n. 可能性；合适的人；可能的事物","adj. 可能的；合理的；合适的"]},"l":"EN2zh-CHS"}
