{"web":[{"value":["范围","值域","全距"],"key":"Range"},{"value":["动态范围","动态范围","动态规模"],"key":"Dynamic Range"},{"value":["四分差","四分位距","四分差"],"key":"interquartile range"}],"query":"range","translation":["范围"],"errorCode":"0","dict":{"url":"yddict://m.youdao.com/dict?le=eng&q=range"},"webdict":{"url":"http://m.youdao.com/dict?le=eng&q=range"},"basic":{"us-phonetic":"rendʒ","phonetic":"reɪn(d)ʒ","uk-phonetic":"reɪn(d)ʒ","explains":["n. 范围；幅度；排；山脉","vt. 漫游；放牧；使并列；归类于；来回走动","vi. （在...内）变动；平行，列为一行；延伸；漫游；射程达到"]},"l":"EN2zh-CHS"}
