{"web":[{"value":["Raw image format","未加工的","生的"],"key":"RAW"},{"value":["建立一个原始连接","原始套接字","套接字"],"key":"Raw Socket"},{"value":["原水","生水","未经净化水"],"key":"raw water"}],"query":"raw","translation":["生"],"errorCode":"0","dict":{"url":"yddict://m.youdao.com/dict?le=eng&q=raw"},"webdict":{"url":"http://m.youdao.com/dict?le=eng&q=raw"},"basic":{"us-phonetic":"rɔ","phonetic":"rɔː","uk-phonetic":"rɔː","explains":["n. 擦伤处","adj. 生的；未加工的；阴冷的；刺痛的；擦掉皮的；无经验的；（在艺术等方面）不成熟的","vt. 擦伤","n. (Raw)人名；(英)罗"]},"l":"EN2zh-CHS"}
