{"web":[{"value":["再分布","重新分配","再分配"],"key":"redistribution"},{"value":["半动态再发布"],"key":"semibynamic redistribution"},{"value":["功率再分布"],"key":"power redistribution"}],"query":"redistribution","translation":["再分配"],"errorCode":"0","dict":{"url":"yddict://m.youdao.com/dict?le=eng&q=redistribution"},"webdict":{"url":"http://m.youdao.com/dict?le=eng&q=redistribution"},"basic":{"us-phonetic":",ri:distri'bju:ʃən","phonetic":",ri:distri'bju:ʃən","uk-phonetic":",ri:distri'bju:ʃən","explains":["n. [经] 重新分配"]},"l":"EN2zh-CHS"}
