{"web":[{"value":["相对论","相对性","相关性"],"key":"Relativity"},{"value":["广义相对论","广义相对论","一般相对论"],"key":"general relativity"},{"value":["对象相关性","主体相对性"],"key":"Agent relativity"}],"query":"relativity","translation":["相对论"],"errorCode":"0","dict":{"url":"yddict://m.youdao.com/dict?le=eng&q=relativity"},"webdict":{"url":"http://m.youdao.com/dict?le=eng&q=relativity"},"basic":{"us-phonetic":",rɛlə'tɪvəti","phonetic":"relə'tɪvɪtɪ","uk-phonetic":"relə'tɪvɪtɪ","explains":["n. 相对论；相关性；相对性"]},"l":"EN2zh-CHS"}
