{"web":[{"value":["返回","送还","回来"],"key":"Return"},{"value":["回佣","回拥","回扣"],"key":"return commission"},{"value":["永恒轮回","永恒轮回","永劫回归"],"key":"Eternal return"}],"query":"return","translation":["返回"],"errorCode":"0","dict":{"url":"yddict://m.youdao.com/dict?le=eng&q=return"},"webdict":{"url":"http://m.youdao.com/dict?le=eng&q=return"},"basic":{"us-phonetic":"rɪ'tɝn","phonetic":"rɪ'tɜːn","uk-phonetic":"rɪ'tɜːn","explains":["vi. 返回；报答","adj. 报答的；回程的；返回的","vt. 返回；报答","n. 返回；归还；回球"]},"l":"EN2zh-CHS"}
