{"web":[{"value":["地震","休克","震惊"],"key":"shock"},{"value":["触电","Electric Shock","Electric Shock"],"key":"electric shock"},{"value":["文化冲击","文化休克","文化冲突"],"key":"Cultural shock"}],"query":"shock","translation":["冲击"],"errorCode":"0","dict":{"url":"yddict://m.youdao.com/dict?le=eng&q=shock"},"webdict":{"url":"http://m.youdao.com/dict?le=eng&q=shock"},"basic":{"us-phonetic":"ʃɑk","phonetic":"ʃɒk","uk-phonetic":"ʃɒk","explains":["n. 休克；震惊；震动；打击；禾束堆","adj. 浓密的；蓬乱的","vt. 使休克；使震惊；使震动；使受电击；把\u2026堆成禾束堆","vi. 感到震惊；受到震动；堆成禾束堆","n. (Shock)人名；(英)肖克"]},"l":"EN2zh-CHS"}
