{"web":[{"value":["略知","少数","一知半解"],"key":"smattering"},{"value":["一知半解"],"key":"a smattering"},{"value":["少数几个"],"key":"a smattering of"}],"query":"smattering","translation":["少数"],"errorCode":"0","dict":{"url":"yddict://m.youdao.com/dict?le=eng&q=smattering"},"webdict":{"url":"http://m.youdao.com/dict?le=eng&q=smattering"},"basic":{"us-phonetic":"'smætərɪŋ","phonetic":"'smætərɪŋ","uk-phonetic":"'smætəriŋ","explains":["n. 一知半解；少数；略知","adj. 肤浅的；些许的；点滴的","v. 略知；肤浅地学习；粉碎（smatter的ing形式）"]},"l":"EN2zh-CHS"}
