{"web":[{"value":["精神的","心灵","精神上的"],"key":"spiritual"},{"value":["退修会","退修会"],"key":"spiritual retreat"},{"value":["精神领袖","得道者"],"key":"spiritual leader"}],"query":"spiritual","translation":["精神上的"],"errorCode":"0","dict":{"url":"yddict://m.youdao.com/dict?le=eng&q=spiritual"},"webdict":{"url":"http://m.youdao.com/dict?le=eng&q=spiritual"},"basic":{"us-phonetic":"'spɪrɪtʃʊəl","phonetic":"'spɪrɪtʃʊəl; -tjʊəl","uk-phonetic":"'spɪrɪtʃʊəl; -tjʊəl","explains":["n. 圣歌（尤指美国南部黑人的）","adj. 精神的，心灵的"]},"l":"EN2zh-CHS"}
