{"web":[{"value":["灭菌","杀菌","消毒"],"key":"sterilization"},{"value":["间歇灭菌法","间歇杀菌","间歇蒸气灭菌法"],"key":"fractional sterilization"},{"value":["辐射灭菌","放射线灭菌法","辐照杀菌"],"key":"radiation sterilization"}],"query":"sterilization","translation":["灭菌"],"errorCode":"0","dict":{"url":"yddict://m.youdao.com/dict?le=eng&q=sterilization"},"webdict":{"url":"http://m.youdao.com/dict?le=eng&q=sterilization"},"basic":{"us-phonetic":",stɛrəlɪ'zeʃən","phonetic":",sterəlaɪ'zeɪʃən","uk-phonetic":",sterəlaɪ'zeɪʃən","explains":["[医][食品] 杀菌；使不孕；无用状态"]},"l":"EN2zh-CHS"}
