{"web":[{"value":["超导的","超导电","超导，超导体的"],"key":"superconducting"},{"value":["超导元素"],"key":"superconducting elements"},{"value":["超导金属"],"key":"superconducting metal"}],"query":"superconducting","translation":["超导"],"errorCode":"0","dict":{"url":"yddict://m.youdao.com/dict?le=eng&q=superconducting"},"webdict":{"url":"http://m.youdao.com/dict?le=eng&q=superconducting"},"basic":{"us-phonetic":",sju:pəkən'dʌktiŋ","phonetic":",sju:pəkən'dʌktiŋ","uk-phonetic":",sju:pəkən'dʌktiŋ","explains":["adj. [低温] 超导的","v. 起超导体作用（superconduct的ing形式）"]},"l":"EN2zh-CHS"}
