{"web":[{"value":["副刊","补充","附录"],"key":"supplement"},{"value":["营养成分","成分表","服法"],"key":"Supplement Facts"},{"value":["补充治疗","补充疗法","弥补治疗"],"key":"supplement therapy"}],"query":"supplement","translation":["补充"],"errorCode":"0","dict":{"url":"yddict://m.youdao.com/dict?le=eng&q=supplement"},"webdict":{"url":"http://m.youdao.com/dict?le=eng&q=supplement"},"basic":{"us-phonetic":"'sʌplɪmənt","phonetic":"'sʌplɪm(ə)nt","uk-phonetic":"'sʌplɪm(ə)nt","explains":["vt. 增补，补充","n. 增补，补充；补充物；增刊，副刊"]},"l":"EN2zh-CHS"}
