{"web":[{"value":["立体的","立体化","立体式"],"key":"three-dimensional"},{"value":["三维流动"],"key":"three-- dimensional flow"},{"value":["空间计算理论"],"key":"three-- dimensional theory"}],"query":"three-dimensional","translation":["三维"],"errorCode":"0","dict":{"url":"yddict://m.youdao.com/dict?le=eng&q=three-dimensional"},"webdict":{"url":"http://m.youdao.com/dict?le=eng&q=three-dimensional"},"basic":{"us-phonetic":"'θridaɪ'mɛnʃənəl","phonetic":"'θri:di'menʃənəl, -dai-","uk-phonetic":"'θri:di'menʃənəl, -dai-","explains":["adj. 三维的；立体的；真实的"]},"l":"EN2zh-CHS"}
