{"web":[{"value":["交易","事务","事务处理"],"key":"Transaction"},{"value":["交易成本","交易费用","交易成本"],"key":"Transaction cost"},{"value":["会计事项","帐务交易","会计业务"],"key":"accounting transaction"}],"query":"transaction","translation":["事务"],"errorCode":"0","dict":{"url":"yddict://m.youdao.com/dict?le=eng&q=transaction"},"webdict":{"url":"http://m.youdao.com/dict?le=eng&q=transaction"},"basic":{"us-phonetic":"træn'zækʃən","phonetic":"træn'zækʃ(ə)n; trɑːn-; -'sæk-","uk-phonetic":"træn'zækʃ(ə)n; trɑːn-; -'sæk-","explains":["n. 交易；事务；办理；会报，学报"]},"l":"EN2zh-CHS"}
