{"web":[{"value":["翻筋斗","跌倒","下跌"],"key":"tumble"},{"value":["用烘干机烘干","滚筒式烘干","烘干"],"key":"Tumble Dry"},{"value":["苦命服务生","服务生"],"key":"Tumble Waiter"}],"query":"tumble","translation":["下跌"],"errorCode":"0","dict":{"url":"yddict://m.youdao.com/dict?le=eng&q=tumble"},"webdict":{"url":"http://m.youdao.com/dict?le=eng&q=tumble"},"basic":{"us-phonetic":"'tʌmbl","phonetic":"'tʌmb(ə)l","uk-phonetic":"'tʌmb(ə)l","explains":["n. 跌倒；翻筋斗；跌跤","vt. 使摔倒；使滚翻；弄乱","vi. 摔倒；倒塌；滚动；打滚；仓惶地行动","[ 过去式tumbled 过去分词tumbled 现在分词tumbling ]"]},"l":"EN2zh-CHS"}
