{"web":[{"value":["不停的","连续的","不断的"],"key":"uninterrupted"},{"value":["无停电运行"],"key":"uninterrupted operation"},{"value":["不间断性"],"key":"uninterrupted nature"}],"query":"uninterrupted","translation":["不间断"],"errorCode":"0","dict":{"url":"yddict://m.youdao.com/dict?le=eng&q=uninterrupted"},"webdict":{"url":"http://m.youdao.com/dict?le=eng&q=uninterrupted"},"basic":{"us-phonetic":",ʌn,ɪntə'rʌptɪd","phonetic":",ʌnɪntə'rʌptɪd","uk-phonetic":",ʌnɪntə'rʌptɪd","explains":["adj. 不间断的；连续的"]},"l":"EN2zh-CHS"}
