{"web":[{"value":["无限","Unlimited (杨千嬅专辑)","无限 (飞儿乐团专辑)"],"key":"Unlimited"},{"value":["无限公司","无限责任公司","无穷公司"],"key":"unlimited company"},{"value":["生活无限","生活无穷"],"key":"Life Unlimited"}],"query":"unlimited","translation":["无限的"],"errorCode":"0","dict":{"url":"yddict://m.youdao.com/dict?le=eng&q=unlimited"},"webdict":{"url":"http://m.youdao.com/dict?le=eng&q=unlimited"},"basic":{"us-phonetic":"ʌn'lɪmɪtɪd","phonetic":"ʌn'lɪmɪtɪd","uk-phonetic":"ʌn'lɪmɪtɪd","explains":["adj. 无限制的；无限量的；无条件的"]},"l":"EN2zh-CHS"}
