{"web":[{"value":["什么时候","何时","时间"],"key":"When"},{"value":["记得当时","曾几何时","记妥当时"],"key":"Remember When"},{"value":["只有在最后渲染时才重新计算更新效果","渲染时"],"key":"When Rendering"}],"query":"when","translation":["何时"],"errorCode":"0","dict":{"url":"yddict://m.youdao.com/dict?le=eng&q=when"},"webdict":{"url":"http://m.youdao.com/dict?le=eng&q=when"},"basic":{"us-phonetic":"hwen; hwɛn","phonetic":"wen","uk-phonetic":"wen","explains":["conj. 考虑到；既然；当\u2026时；在\u2026时；如果","n. 时间，时候；日期；场合","adv. 什么时候，何时；（用于时间的表达方式之后）在那时；其时；当时","pron. 那时；什么时侯"]},"l":"EN2zh-CHS"}
